{"stat.walkOneCm":17699,"stat.mineBlock.minecraft.stone_button":3,"stat.leaveGame":2,"stat.useItem.minecraft.skull":1,"stat.pickup.minecraft.flower_pot":2,"stat.useItem.minecraft.flower_pot":7,"stat.jump":48,"stat.useItem.minecraft.sand":17,"stat.fallOneCm":476,"stat.useItem.minecraft.end_rod":2,"stat.useItem.minecraft.piston":3,"stat.useItem.minecraft.spruce_stairs":7,"stat.crouchOneCm":615,"stat.useItem.minecraft.stone_button":7,"stat.sprintOneCm":6172,"stat.pickup.minecraft.ladder":1,"stat.pickup.minecraft.skull":1,"stat.useItem.minecraft.diamond_pickaxe":1,"stat.useItem.minecraft.rail":5,"stat.useItem.minecraft.scenarium":1,"stat.useItem.minecraft.anvil":14,"stat.useItem.minecraft.golden_apple":1,"stat.flyOneCm":15349,"stat.playOneMinute":10563,"stat.pickup.minecraft.stone_button":4,"stat.useItem.minecraft.ladder":3,"stat.sneakTime":258,"stat.useItem.minecraft.snow_layer":5,"stat.timeSinceDeath":10563}